FangEngine/__init__.py
FangEngine/error_log.py
FangEngine/exceptions.py
FangEngine/graphics_options.py
FangEngine/image_utils.py
FangEngine/status_codes.py
FangEngine/converter/__init__.py
FangEngine/converter/angle.py
FangEngine/converter/color.py
FangEngine/display_methods/__init__.py
FangEngine/display_methods/sprite_sheet.py
FangEngine/game_object/__init__.py
FangEngine/game_object/game_object.py
FangEngine/game_object/hitbox.py
FangEngine/game_object/layer/__init__.py
FangEngine/game_object/layer/base_layer.py
FangEngine/game_object/premade/__init__.py
FangEngine/game_object/premade/character.py
FangEngine/game_object/premade/character_button.py
FangEngine/game_object/premade/rotatable_object.py
FangEngine/game_object/premade/rotatable_sprite_sheet.py
FangEngine/game_object/premade/rotatable_text.py
FangEngine/game_object/premade/text.py
FangEngine/game_object/premade/hud/__init__.py
FangEngine/game_object/premade/hud/hud_base.py
FangEngine/game_object/premade/hud/variable_hud.py
FangEngine/screen_manager/__init__.py
FangEngine/screen_manager/base_screen.py
FangEngine/screen_manager/camera.py
FangEngine/screen_manager/dialog_box.py
FangEngine/screen_manager/image_dialog_box.py
FangEngine/screen_manager/object_screen.py
FangEngine/screen_manager/screen_manager.py
FangEngine/screen_manager/grid_screen/__init__.py
FangEngine/screen_manager/grid_screen/base_grid_screen.py
FangEngine/screen_manager/rotatable_screen/__init__.py
FangEngine/screen_manager/rotatable_screen/rotatable_screen_base.py
FangEngine/screen_manager/terminal_screen/__init__.py
FangEngine/screen_manager/terminal_screen/base_console_screen.py
FangEngine/screen_manager/terminal_screen/base_terminal_screen.py
FangEngine/screen_manager/terminal_screen/system_console_screen.py
FangEngine/store/__init__.py
FangEngine/store/control_store.py
FangEngine/store/language_store.py
FangEngine/store/asset_store/__init__.py
FangEngine/store/asset_store/asset_store.py
FangEngine-0.1.2.dist-info/LICENSE
FangEngine-0.1.2.dist-info/METADATA
FangEngine-0.1.2.dist-info/WHEEL
FangEngine-0.1.2.dist-info/top_level.txt
FangEngine-0.1.2.dist-info/RECORD
