Metadata-Version: 2.1
Name: FangEngine
Version: 0.1.2
Summary: This engine allows you to easily create object oriented, event-driven games in Python! You can customize as much or as little of the engine as you need to build your next great game!
Home-page: https://github.com/CPSuperstore/FangEngineDocs
Author: CPSuperstore
Author-email: cpsuperstoreinc@gmail.com
License: UNKNOWN
Project-URL: Bug Tracker, https://github.com/CPSuperstore/FangEngineDocs/issues
Project-URL: Documentation, https://github.com/CPSuperstore/FangEngineDocs/wiki
Platform: UNKNOWN
Classifier: Programming Language :: Python :: 3
Classifier: Operating System :: OS Independent
Classifier: Development Status :: 4 - Beta
Classifier: License :: OSI Approved :: GNU Lesser General Public License v2 or later (LGPLv2+)
Classifier: Natural Language :: English
Classifier: Intended Audience :: Developers
Classifier: Intended Audience :: Information Technology
Classifier: Operating System :: Microsoft :: Windows
Classifier: Operating System :: MacOS
Classifier: Operating System :: POSIX
Classifier: Operating System :: Unix
Classifier: Topic :: Desktop Environment
Classifier: Topic :: Games/Entertainment
Classifier: Topic :: Multimedia :: Graphics
Classifier: Topic :: Multimedia :: Sound/Audio
Classifier: Topic :: Software Development
Requires-Python: >=3.6
License-File: LICENSE
